CHANGES.txt
CONTRIBUTORS.txt
MANIFEST.in
README.txt
setup.cfg
setup.py
docs/HISTORY.txt
docs/INSTALL.txt
docs/LICENSE.GPL
docs/LICENSE.txt
ploneorg/__init__.py
ploneorg.kudobounty.egg-info/PKG-INFO
ploneorg.kudobounty.egg-info/SOURCES.txt
ploneorg.kudobounty.egg-info/dependency_links.txt
ploneorg.kudobounty.egg-info/entry_points.txt
ploneorg.kudobounty.egg-info/namespace_packages.txt
ploneorg.kudobounty.egg-info/not-zip-safe
ploneorg.kudobounty.egg-info/requires.txt
ploneorg.kudobounty.egg-info/top_level.txt
ploneorg/kudobounty/README.txt
ploneorg/kudobounty/__init__.py
ploneorg/kudobounty/config.py
ploneorg/kudobounty/configure.zcml
ploneorg/kudobounty/interfaces.py
ploneorg/kudobounty/setuphandlers.py
ploneorg/kudobounty/browser/__init__.py
ploneorg/kudobounty/browser/bounty_collection_view.pt
ploneorg/kudobounty/browser/bountysubmission_view.pt
ploneorg/kudobounty/browser/configure.zcml
ploneorg/kudobounty/browser/ploneorg_bounty.css
ploneorg/kudobounty/browser/ploneorg_bounty.js
ploneorg/kudobounty/browser/views.py
ploneorg/kudobounty/content/__init__.py
ploneorg/kudobounty/content/bountyprogramsubmission.py
ploneorg/kudobounty/content/configure.zcml
ploneorg/kudobounty/profiles/default/cssregistry.xml
ploneorg/kudobounty/profiles/default/factorytool.xml
ploneorg/kudobounty/profiles/default/jsregistry.xml
ploneorg/kudobounty/profiles/default/metadata.xml
ploneorg/kudobounty/profiles/default/ploneorg_kudobounty.txt
ploneorg/kudobounty/profiles/default/rolemap.xml
ploneorg/kudobounty/profiles/default/submissions-form.tar.gz
ploneorg/kudobounty/profiles/default/types.xml
ploneorg/kudobounty/profiles/default/types/Bounty_Program_Submission.xml
ploneorg/kudobounty/profiles/portlets/ploneorg_kudobounty_portlets.txt
ploneorg/kudobounty/profiles/portlets/portlets.xml
ploneorg/kudobounty/tests/__init__.py
ploneorg/kudobounty/tests/base.py
ploneorg/kudobounty/tests/test_doctest.py