Metadata-Version: 1.0
Name: ploneorg.kudobounty
Version: 0.1
Summary: Bounty Program logo display mechanism for the plone.org
Home-page: http://svn.quintagroup.com/products/
Author: mylan at quintagroup.com
Author-email: support@quintagroup.com
License: GPL
Platform: UNKNOWN
Classifier: Framework :: Plone
Classifier: Intended Audience :: Developers
Classifier: License :: OSI Approved :: GNU General Public License (GPL)
